{"name": "umr", "version": "0.1.10", "title": "UMR: Ultimate Modular Reactor", "author": "PreLeyZero", "factorio_version": "1.1", "description": "This mod adds a universal reactor, consisting of different modules. It can turn vanilla and modded fuels into power, furnace or crafting machine fuel. Will supply all the power you ever need!", "dependencies": ["base >= 1.0.0", "Squeak Through", "?Booktorio", "?248k", "?RealisticFusionPower", "?Krastorio2", "?angelsindustries >= 0.4.10", "?Yuoki", "?space-exploration"]}