{"name": "super-generous-recipes", "version": "0.7.0", "title": "Super Generous Recipes", "author": "M4pster", "description": "Speeds up the game for a quicker experience. Lots of settings provided for customization.", "dependencies": ["base", "? Power Armor MK3", "? reverse-factory", "? BobExtended", "? angelspetrochem", "? angelslocaleja_RE", "? aai-industry", "? mini-machines", "? omnimatter_wood", "? Bio_Industries", "? kry-inserters", "? GDIW", "? bobelectronics", "? Fantario", "? pycoalprocessing", "? pyfusionenergy", "? pyhightech", "? pyindustry", "? pypetroleumhandling", "? IndustrialRevolution", "? RPGsystem", "? FactorioExtended-Plus-CompoundSolars", "? FactorioExtended-Plus-Core", "? FactorioExtended-Plus-Equipment", "? FactorioExtended-Plus-Logistics", "? FactorioExtended-Plus-Machines", "? FactorioExtended-Plus-Module", "? FactorioExtended-Plus-Power", "? FactorioExtended-Plus-Storage", "? FactorioExtended-Plus-Transport", "? FactorioExtended-Plus-Weaponry", "? bobassembly", "? bobclasses", "? bobelectronics", "? bobenemies", "? bobequipment", "? boblibrary", "? boblogistics", "? bobmining", "? bobmodules", "? bobores", "? bobplates", "? bobpower", "? bobrevamp", "? bobtech", "? bobvehicleequipment", "? bobwarfare", "? Krastorio2", "? VoidChestPlus", "? Nanobots", "? space-exploration-postprocess"], "factorio_version": "1.1"}