{"name": "some-disableenemygeneration", "version": "1.1.0", "title": "Disable enemy generation", "author": "someone1337", "homepage": "https://git.somenet.org/factorio/some-disableenemygeneration.git", "description": "Enable mod to disable the spawning of enemy bases on newly generated chunks. Disable mod to restore vanilla behavior. This way you can go mega without having to use lua commands (=losing achievements) or restart the game. Existing enemies may still expand on their own!", "dependencies": ["base>=1.1.0"], "factorio_version": "1.1"}