{"name": "wrqleasypy", "version": "0.18.2", "factorio_version": "0.18", "title": "Wrql's Easy Py Lottery system", "author": "Wei-ren-qu-liu", "contact": "Wrql's QQ group:859914117 Personal QQ\uff1a919475700", "homepage": "https://www.zlfgame.club/", "dependencies": ["base >= 0.18.0"], "description": "A set of random formula and item conversion are added to make py series mod easier, and the function of auxiliary random property is added without changing the original difficulty. \u589e\u52a0\u4e86\u4e00\u7ec4\u968f\u673a\u914d\u65b9\u548c\u7269\u54c1\u8f6c\u6362\u6765\u4f7f\u5f97py\u7cfb\u5217mod\u663e\u5f97\u66f4\u5bb9\u6613\uff0c\u5728\u4e0d\u6539\u53d8\u539f\u6709\u96be\u5ea6\u7684\u57fa\u7840\u4e0a\u589e\u52a0\u7684\u8f85\u52a9\u968f\u673a\u6027\u8d28\u7684\u529f\u80fd"}